async_stream_magic/__init__.py
async_stream_magic/__version__.py
async_stream_magic/exceptions.py
async_stream_magic/models.py
async_stream_magic/stream_magic.py
async_stream_magic-0.1.6.dist-info/METADATA
async_stream_magic-0.1.6.dist-info/WHEEL
async_stream_magic-0.1.6.dist-info/licenses/LICENSE
async_stream_magic-0.1.6.dist-info/RECORD
